plutous/__init__.py
plutous/trade/__init__.py
plutous/trade/alembic.ini
plutous/trade/app/__init__.py
plutous/trade/app/main.py
plutous/trade/app/models.py
plutous/trade/cli/__init__.py
plutous/trade/cli/database.py
plutous/trade/cli/main.py
plutous/trade/enums/__init__.py
plutous/trade/enums/action.py
plutous/trade/enums/asset_type.py
plutous/trade/enums/bot_type.py
plutous/trade/enums/position_side.py
plutous/trade/enums/strategy_direction.py
plutous/trade/enums/strategy_type.py
plutous/trade/migrations/README
plutous/trade/migrations/env.py
plutous/trade/migrations/script.py.mako
plutous/trade/migrations/versions/2023-05-23_03-57_3e037c0f4152_init.py
plutous/trade/models/__init__.py
plutous/trade/models/api_key.py
plutous/trade/models/base.py
plutous/trade/models/bot.py
plutous/trade/models/position.py
plutous/trade/models/strategy.py
plutous/trade/models/trade.py
plutous_trade-0.0.24.dist-info/LICENSE
plutous_trade-0.0.24.dist-info/METADATA
plutous_trade-0.0.24.dist-info/WHEEL
plutous_trade-0.0.24.dist-info/RECORD
