Metadata-Version: 2.1
Name: plutous-trade
Version: 0.0.24
Summary: Plutous Trading Library
License: MIT
Author: Cheun Hong
Author-email: cheunhong@plutous.io
Requires-Python: >=3.11,<3.12
Classifier: Intended Audience :: Developers
Classifier: License :: OSI Approved :: MIT License
Classifier: Operating System :: OS Independent
Classifier: Programming Language :: Python :: 3
Classifier: Programming Language :: Python :: 3.11
Requires-Dist: plutous (>=0.0.1)
